hanzo_repl/__init__.py
hanzo_repl/backends.py
hanzo_repl/cli.py
hanzo_repl/command_palette.py
hanzo_repl/command_suggestions.py
hanzo_repl/ipython_repl.py
hanzo_repl/llm_client.py
hanzo_repl/repl.py
hanzo_repl/tests.py
hanzo_repl/textual_repl.py
hanzo_repl/tool_executor.py
hanzo_repl/voice_mode.py
hanzo_repl-0.1.0.dist-info/METADATA
hanzo_repl-0.1.0.dist-info/WHEEL
hanzo_repl-0.1.0.dist-info/entry_points.txt
hanzo_repl-0.1.0.dist-info/RECORD
