Metadata-Version: 2.4
Name: hanzo-repl
Version: 0.1.0
Summary: Interactive REPL for Hanzo AI - Like Claude Code in your terminal
Project-URL: Homepage, https://hanzo.ai
Project-URL: Documentation, https://docs.hanzo.ai/repl
Project-URL: Repository, https://github.com/hanzoai/python-sdk
Project-URL: Issues, https://github.com/hanzoai/python-sdk/issues
Author-email: Hanzo AI <dev@hanzo.ai>
License: BSD-3-Clause
Keywords: ai,claude,hanzo,interactive,llm,mcp,repl
Classifier: Development Status :: 4 - Beta
Classifier: Environment :: Console
Classifier: Intended Audience :: Developers
Classifier: License :: OSI Approved :: BSD License
Classifier: Programming Language :: Python :: 3
Classifier: Programming Language :: Python :: 3.8
Classifier: Programming Language :: Python :: 3.9
Classifier: Programming Language :: Python :: 3.10
Classifier: Programming Language :: Python :: 3.11
Classifier: Programming Language :: Python :: 3.12
Classifier: Topic :: Scientific/Engineering :: Artificial Intelligence
Classifier: Topic :: Software Development :: Libraries :: Python Modules
Classifier: Topic :: Software Development :: Testing
Requires-Python: >=3.8
Requires-Dist: click>=8.0.0
Requires-Dist: colorama>=0.4.6
Requires-Dist: hanzo-mcp>=0.1.0
Requires-Dist: ipython>=8.0.0
Requires-Dist: litellm>=1.0.0
Requires-Dist: prompt-toolkit>=3.0.0
Requires-Dist: pygments>=2.17.0
Requires-Dist: python-dotenv>=1.0.0
Requires-Dist: rich>=13.0.0
Requires-Dist: textual>=0.41.0
Provides-Extra: dev
Requires-Dist: black>=23.0.0; extra == 'dev'
Requires-Dist: mypy>=1.0.0; extra == 'dev'
Requires-Dist: pytest-asyncio>=0.21.0; extra == 'dev'
Requires-Dist: pytest-cov>=4.0.0; extra == 'dev'
Requires-Dist: pytest>=7.0.0; extra == 'dev'
Requires-Dist: ruff>=0.1.0; extra == 'dev'
Provides-Extra: voice
Requires-Dist: numpy>=1.24.0; extra == 'voice'
Requires-Dist: pyaudio>=0.2.11; extra == 'voice'
Requires-Dist: pyttsx3>=2.90; extra == 'voice'
Requires-Dist: sounddevice>=0.4.6; extra == 'voice'
Requires-Dist: speechrecognition>=3.10.0; extra == 'voice'
